kalib/__init__.py
kalib/dataclass.py
kalib/datastructures.py
kalib/exceptions.py
kalib/halt.py
kalib/hypertext.py
kalib/loggers.py
kalib/misc.py
kalib/redis.py
kalib/text.py
kalib/versions.py
kalib-0.22.4.dist-info/METADATA
kalib-0.22.4.dist-info/WHEEL
kalib-0.22.4.dist-info/top_level.txt
kalib-0.22.4.dist-info/RECORD
