Metadata-Version: 2.4
Name: kalib
Version: 0.22.4
Summary: A comprehensive set of advanced utilities for Python programming, e.g. HTTP communication, string handling, logging enhancements, introspection, dynamic importing, property caching descriptors, data class extensions, serialization, etc.
Author-email: Alex Kalaverin <alex@kalaver.in>
License: BSD License
Keywords: dataclass,decorators,descriptors,http,import,introspection,logging,python,serialization,string,utilities
Classifier: Development Status :: 5 - Production/Stable
Classifier: Intended Audience :: Developers
Classifier: Topic :: Software Development :: Libraries :: Python Modules
Classifier: Programming Language :: Python
Classifier: Programming Language :: Python :: 3
Classifier: Programming Language :: Python :: 3.10
Classifier: Programming Language :: Python :: 3.11
Classifier: License :: OSI Approved :: BSD License
Classifier: Operating System :: OS Independent
Requires-Python: <3.13,>=3.10
Requires-Dist: charded>=0.1.0
Requires-Dist: kain<0.2.0,>=0.1.4
Provides-Extra: data
Requires-Dist: base2048>=0.1.3; extra == "data"
Requires-Dist: fake-useragent>=2.2.0; extra == "data"
Requires-Dist: feedparser>=6.0.11; extra == "data"
Requires-Dist: lxml>=5.4.0; extra == "data"
Requires-Dist: msgpack>=1.1.0; extra == "data"
Requires-Dist: yarl>=1.20.0; extra == "data"
Provides-Extra: redis
Requires-Dist: hiredis>=3.2.1; extra == "redis"
Requires-Dist: redis-lock-py>=1.1.1; extra == "redis"
Requires-Dist: redis>=6.2.0; extra == "redis"
Provides-Extra: usual
Requires-Dist: natsort>=8.4.0; extra == "usual"
Requires-Dist: orjson>=3.10.16; extra == "usual"
Requires-Dist: xxhash>=3.5.0; extra == "usual"
Requires-Dist: zstd>=1.5.6.7; extra == "usual"
